requests_iam_session/__init__.py
requests_iam_session-0.2.2.dist-info/LICENSE
requests_iam_session-0.2.2.dist-info/WHEEL
requests_iam_session-0.2.2.dist-info/METADATA
requests_iam_session-0.2.2.dist-info/RECORD
